<?xml version="1.0" encoding="utf-8" ?>
<dwsync>
<file name="Database.php" server="ftp.duotics.com//public_html/demo/ecuahomes/admin/" local="131631685490356399" remote="131632131600000000" Dst="0" />
<file name="DateTime.php" server="ftp.duotics.com//public_html/demo/ecuahomes/admin/" local="131631685484249837" remote="131632131600000000" Dst="0" />
<file name="Exception.php" server="ftp.duotics.com//public_html/demo/ecuahomes/admin/" local="131631685477042180" remote="131632131600000000" Dst="0" />
<file name="ExceptionHandler.php" server="ftp.duotics.com//public_html/demo/ecuahomes/admin/" local="131631685472889333" remote="131632131600000000" Dst="0" />
<file name="Engineering.php" server="ftp.duotics.com//public_html/demo/ecuahomes/admin/" local="131631685486616518" remote="131632131600000000" Dst="0" />
<file name="FormulaParser.php" server="ftp.duotics.com//public_html/demo/ecuahomes/admin/" local="131631685468680115" remote="131632131600000000" Dst="0" />
<file name="Financial.php" server="ftp.duotics.com//public_html/demo/ecuahomes/admin/" local="131631685476470527" remote="131632131600000000" Dst="0" />
<file name="FormulaToken.php" server="ftp.duotics.com//public_html/demo/ecuahomes/admin/" local="131631685467095707" remote="131632131600000000" Dst="0" />
<file name="Function.php" server="ftp.duotics.com//public_html/demo/ecuahomes/admin/" local="131631685463342196" remote="131632131600000000" Dst="0" />
<file name="functionlist.txt" server="ftp.duotics.com//public_html/demo/ecuahomes/admin/" local="131631685443638796" remote="131632131600000000" Dst="0" />
<file name="Functions.php" server="ftp.duotics.com//public_html/demo/ecuahomes/admin/" local="131631685462950840" remote="131632131600000000" Dst="0" />
<file name="Logical.php" server="ftp.duotics.com//public_html/demo/ecuahomes/admin/" local="131631685458997156" remote="131632131600000000" Dst="0" />
<file name="LookupRef.php" server="ftp.duotics.com//public_html/demo/ecuahomes/admin/" local="131631685457724834" remote="131632131600000000" Dst="0" />
<file name="MathTrig.php" server="ftp.duotics.com//public_html/demo/ecuahomes/admin/" local="131631685452474053" remote="131632131600000000" Dst="0" />
<file name="TextData.php" server="ftp.duotics.com//public_html/demo/ecuahomes/admin/" local="131631685446284741" remote="131632131600000000" Dst="0" />
<file name="Statistical.php" server="ftp.duotics.com//public_html/demo/ecuahomes/admin/" local="131631685454869996" remote="131632131600000000" Dst="0" />
<file name="Database.php" server="ftp.ecuahomes.net//public_html/admin/" local="131631685490356399" remote="131670824400000000" Dst="0" />
<file name="DateTime.php" server="ftp.ecuahomes.net//public_html/admin/" local="131631685484249837" remote="131670824400000000" Dst="0" />
<file name="Exception.php" server="ftp.ecuahomes.net//public_html/admin/" local="131631685477042180" remote="131670824400000000" Dst="0" />
<file name="ExceptionHandler.php" server="ftp.ecuahomes.net//public_html/admin/" local="131631685472889333" remote="131670824400000000" Dst="0" />
<file name="Engineering.php" server="ftp.ecuahomes.net//public_html/admin/" local="131631685486616518" remote="131670824400000000" Dst="0" />
<file name="FormulaParser.php" server="ftp.ecuahomes.net//public_html/admin/" local="131631685468680115" remote="131670824400000000" Dst="0" />
<file name="Financial.php" server="ftp.ecuahomes.net//public_html/admin/" local="131631685476470527" remote="131670824400000000" Dst="0" />
<file name="FormulaToken.php" server="ftp.ecuahomes.net//public_html/admin/" local="131631685467095707" remote="131670824400000000" Dst="0" />
<file name="Function.php" server="ftp.ecuahomes.net//public_html/admin/" local="131631685463342196" remote="131670824400000000" Dst="0" />
<file name="functionlist.txt" server="ftp.ecuahomes.net//public_html/admin/" local="131631685443638796" remote="131670824400000000" Dst="0" />
<file name="Functions.php" server="ftp.ecuahomes.net//public_html/admin/" local="131631685462950840" remote="131670824400000000" Dst="0" />
<file name="Logical.php" server="ftp.ecuahomes.net//public_html/admin/" local="131631685458997156" remote="131670824400000000" Dst="0" />
<file name="LookupRef.php" server="ftp.ecuahomes.net//public_html/admin/" local="131631685457724834" remote="131670824400000000" Dst="0" />
<file name="MathTrig.php" server="ftp.ecuahomes.net//public_html/admin/" local="131631685452474053" remote="131670824400000000" Dst="0" />
<file name="Statistical.php" server="ftp.ecuahomes.net//public_html/admin/" local="131631685454869996" remote="131670824400000000" Dst="0" />
<file name="TextData.php" server="ftp.ecuahomes.net//public_html/admin/" local="131631685446284741" remote="131670824400000000" Dst="0" />
<file name="Database.php" server="//Server01/duosoft_netlike/v2/" local="131631685490356399" remote="131631685490000000" Dst="0" />
<file name="DateTime.php" server="//Server01/duosoft_netlike/v2/" local="131631685484249837" remote="131631685480000000" Dst="0" />
<file name="Engineering.php" server="//Server01/duosoft_netlike/v2/" local="131631685486616518" remote="131631685480000000" Dst="0" />
<file name="Exception.php" server="//Server01/duosoft_netlike/v2/" local="131631685477042180" remote="131631685470000000" Dst="0" />
<file name="ExceptionHandler.php" server="//Server01/duosoft_netlike/v2/" local="131631685472889333" remote="131631685470000000" Dst="0" />
<file name="Financial.php" server="//Server01/duosoft_netlike/v2/" local="131631685476470527" remote="131631685470000000" Dst="0" />
<file name="FormulaParser.php" server="//Server01/duosoft_netlike/v2/" local="131631685468680115" remote="131631685460000000" Dst="0" />
<file name="FormulaToken.php" server="//Server01/duosoft_netlike/v2/" local="131631685467095707" remote="131631685460000000" Dst="0" />
<file name="Function.php" server="//Server01/duosoft_netlike/v2/" local="131631685463342196" remote="131631685460000000" Dst="0" />
<file name="functionlist.txt" server="//Server01/duosoft_netlike/v2/" local="131631685443638796" remote="131631685440000000" Dst="0" />
<file name="Functions.php" server="//Server01/duosoft_netlike/v2/" local="131631685462950840" remote="131631685460000000" Dst="0" />
<file name="Logical.php" server="//Server01/duosoft_netlike/v2/" local="131631685458997156" remote="131631685450000000" Dst="0" />
<file name="LookupRef.php" server="//Server01/duosoft_netlike/v2/" local="131631685457724834" remote="131631685450000000" Dst="0" />
<file name="MathTrig.php" server="//Server01/duosoft_netlike/v2/" local="131631685452474053" remote="131631685450000000" Dst="0" />
<file name="Statistical.php" server="//Server01/duosoft_netlike/v2/" local="131631685454869996" remote="131631685450000000" Dst="0" />
<file name="TextData.php" server="//Server01/duosoft_netlike/v2/" local="131631685446284741" remote="131631685440000000" Dst="0" />
</dwsync>