<?xml version="1.0" encoding="utf-8" ?>
<dwsync>
<file name="arrow-left-hover.gif" server="ftp.duotics.com//public_html/demo/ecuahomes/admin/" local="131631685083566926" remote="131632131000000000" Dst="0" />
<file name="arrow-right-hover.gif" server="ftp.duotics.com//public_html/demo/ecuahomes/admin/" local="131631685079310072" remote="131632131000000000" Dst="0" />
<file name="arrow-right.gif" server="ftp.duotics.com//public_html/demo/ecuahomes/admin/" local="131631685077658041" remote="131632131000000000" Dst="0" />
<file name="arrow-left.gif" server="ftp.duotics.com//public_html/demo/ecuahomes/admin/" local="131631685081813057" remote="131632131000000000" Dst="0" />
<file name="background.png" server="ftp.duotics.com//public_html/demo/ecuahomes/admin/" local="131631685073490956" remote="131632131000000000" Dst="0" />
<file name="day.gif" server="ftp.duotics.com//public_html/demo/ecuahomes/admin/" local="131631685071007148" remote="131632131000000000" Dst="0" />
<file name="background.gif" server="ftp.duotics.com//public_html/demo/ecuahomes/admin/" local="131631685075132771" remote="131632131000000000" Dst="0" />
<file name="year-decade.gif" server="ftp.duotics.com//public_html/demo/ecuahomes/admin/" local="131631685069242094" remote="131632131000000000" Dst="0" />
<file name="arrow-left-hover.gif" server="ftp.ecuahomes.net//public_html/admin/" local="131631685083566926" remote="131670823200000000" Dst="0" />
<file name="arrow-left.gif" server="ftp.ecuahomes.net//public_html/admin/" local="131631685081813057" remote="131670823200000000" Dst="0" />
<file name="arrow-right-hover.gif" server="ftp.ecuahomes.net//public_html/admin/" local="131631685079310072" remote="131670823200000000" Dst="0" />
<file name="arrow-right.gif" server="ftp.ecuahomes.net//public_html/admin/" local="131631685077658041" remote="131670823200000000" Dst="0" />
<file name="day.gif" server="ftp.ecuahomes.net//public_html/admin/" local="131631685071007148" remote="131670823200000000" Dst="0" />
<file name="background.gif" server="ftp.ecuahomes.net//public_html/admin/" local="131631685075132771" remote="131670823200000000" Dst="0" />
<file name="background.png" server="ftp.ecuahomes.net//public_html/admin/" local="131631685073490956" remote="131670823200000000" Dst="0" />
<file name="year-decade.gif" server="ftp.ecuahomes.net//public_html/admin/" local="131631685069242094" remote="131670823200000000" Dst="0" />
<file name="arrow-left-hover.gif" server="//Server01/duosoft_netlike/v2/" local="131631685083566926" remote="131631685080000000" Dst="0" />
<file name="arrow-left.gif" server="//Server01/duosoft_netlike/v2/" local="131631685081813057" remote="131631685080000000" Dst="0" />
<file name="arrow-right-hover.gif" server="//Server01/duosoft_netlike/v2/" local="131631685079310072" remote="131631685070000000" Dst="0" />
<file name="arrow-right.gif" server="//Server01/duosoft_netlike/v2/" local="131631685077658041" remote="131631685070000000" Dst="0" />
<file name="background.gif" server="//Server01/duosoft_netlike/v2/" local="131631685075132771" remote="131631685070000000" Dst="0" />
<file name="background.png" server="//Server01/duosoft_netlike/v2/" local="131631685073490956" remote="131631685070000000" Dst="0" />
<file name="day.gif" server="//Server01/duosoft_netlike/v2/" local="131631685071007148" remote="131631685070000000" Dst="0" />
<file name="year-decade.gif" server="//Server01/duosoft_netlike/v2/" local="131631685069242094" remote="131631685060000000" Dst="0" />
</dwsync>