<?xml version="1.0" encoding="utf-8" ?>
<dwsync>
<file name="contact_data.php" server="ftp.duotics.com//public_html/demo/ecuahomes/admin/" local="131631684000570431" remote="131632129800000000" Dst="0" />
<file name="all_data.php" server="ftp.duotics.com//public_html/demo/ecuahomes/admin/" local="131631684003280519" remote="131632129800000000" Dst="0" />
<file name="error_log" server="ftp.duotics.com//public_html/demo/ecuahomes/admin/" local="131631683999175941" remote="131632129800000000" Dst="0" />
<file name="index.php" server="ftp.duotics.com//public_html/demo/ecuahomes/admin/" local="131631683995012771" remote="131632129800000000" Dst="0" />
<file name="fncts.php" server="ftp.duotics.com//public_html/demo/ecuahomes/admin/" local="131631683996361138" remote="131632129800000000" Dst="0" />
<file name="index_mess.php" server="ftp.duotics.com//public_html/demo/ecuahomes/admin/" local="131631683992158372" remote="131632129800000000" Dst="0" />
<file name="rep_excel-maillist.php" server="ftp.duotics.com//public_html/demo/ecuahomes/admin/" local="131631683987511410" remote="131632129800000000" Dst="0" />
<file name="rep_excel.php" server="ftp.duotics.com//public_html/demo/ecuahomes/admin/" local="131631683986253891" remote="131632129800000000" Dst="0" />
<file name="mess_data.php" server="ftp.duotics.com//public_html/demo/ecuahomes/admin/" local="131631683990911025" remote="131632129800000000" Dst="0" />
<file name="all_data.php" server="ftp.ecuahomes.net//public_html/admin/" local="131631684003280519" remote="131670822000000000" Dst="0" />
<file name="contact_data.php" server="ftp.ecuahomes.net//public_html/admin/" local="131631684000570431" remote="131670822000000000" Dst="0" />
<file name="fncts.php" server="ftp.ecuahomes.net//public_html/admin/" local="131631683996361138" remote="131670822000000000" Dst="0" />
<file name="error_log" server="ftp.ecuahomes.net//public_html/admin/" local="131631683999175941" remote="131670822000000000" Dst="0" />
<file name="index.php" server="ftp.ecuahomes.net//public_html/admin/" local="131631683995012771" remote="131670822000000000" Dst="0" />
<file name="mess_data.php" server="ftp.ecuahomes.net//public_html/admin/" local="131631683990911025" remote="131670822000000000" Dst="0" />
<file name="index_mess.php" server="ftp.ecuahomes.net//public_html/admin/" local="131631683992158372" remote="131670822000000000" Dst="0" />
<file name="rep_excel-maillist.php" server="ftp.ecuahomes.net//public_html/admin/" local="131631683987511410" remote="131670822000000000" Dst="0" />
<file name="rep_excel.php" server="ftp.ecuahomes.net//public_html/admin/" local="131631683986253891" remote="131670822600000000" Dst="0" />
<file name="all_data.php" server="//Server01/duosoft_netlike/v2/" local="131631684003280519" remote="131631684000000000" Dst="0" />
<file name="contact_data.php" server="//Server01/duosoft_netlike/v2/" local="131631684000570431" remote="131631684000000000" Dst="0" />
<file name="error_log" server="//Server01/duosoft_netlike/v2/" local="131631683999175941" remote="131631683990000000" Dst="0" />
<file name="fncts.php" server="//Server01/duosoft_netlike/v2/" local="131631683996361138" remote="131631683990000000" Dst="0" />
<file name="index.php" server="//Server01/duosoft_netlike/v2/" local="131631683995012771" remote="131631683990000000" Dst="0" />
<file name="index_mess.php" server="//Server01/duosoft_netlike/v2/" local="131631683992158372" remote="131631683990000000" Dst="0" />
<file name="mess_data.php" server="//Server01/duosoft_netlike/v2/" local="131631683990911025" remote="131631683990000000" Dst="0" />
<file name="rep_excel-maillist.php" server="//Server01/duosoft_netlike/v2/" local="131631683987511410" remote="131631683980000000" Dst="0" />
<file name="rep_excel.php" server="//Server01/duosoft_netlike/v2/" local="131631683986253891" remote="131631683980000000" Dst="0" />
</dwsync>